mtianyan/__init__.py
mtianyan/cv.py
mtianyan/listname.py
mtianyan/path_helper.py
mtianyan/tianyan.py
mtianyan/download_helper/Aria2Commd.py
mtianyan/download_helper/Aria2RpcDownload.py
mtianyan/download_helper/__init__.py
mtianyan/download_helper/aria2.conf
mtianyan/download_helper/aria2.session
mtianyan/download_helper/aria2c.exe
mtianyan/download_helper/download_list.py
mtianyan/download_helper/startAria2Rpc.bat
mtianyan/download_helper/dir/Browse3_jpg.tar.gz
mtianyan/download_helper/dir/Browse3_jpg.tar.gz.aria2
mtianyan/download_helper/dir/Browse4_jpg.tar.gz
mtianyan/download_helper/dir/Browse4_jpg.tar.gz.aria2
mtianyan/plugins/webui-aria2/.dockerignore
mtianyan/plugins/webui-aria2/.gitignore
mtianyan/plugins/webui-aria2/Dockerfile
mtianyan/plugins/webui-aria2/Dockerfile.arm
mtianyan/plugins/webui-aria2/LICENSE
mtianyan/plugins/webui-aria2/README.md
mtianyan/plugins/webui-aria2/app.json
mtianyan/plugins/webui-aria2/configuration.js
mtianyan/plugins/webui-aria2/directurl.md
mtianyan/plugins/webui-aria2/docker-compose.yml
mtianyan/plugins/webui-aria2/favicon.ico
mtianyan/plugins/webui-aria2/index.html
mtianyan/plugins/webui-aria2/node-server.js
mtianyan/plugins/webui-aria2/package-lock.json
mtianyan/plugins/webui-aria2/static.json
mtianyan/plugins/webui-aria2/webui-aria2.spec
mtianyan/plugins/webui-aria2/css/bootstrap.min.css
mtianyan/plugins/webui-aria2/css/download.css
mtianyan/plugins/webui-aria2/css/flag-icon.min.css
mtianyan/plugins/webui-aria2/css/font-awesome.min.css
mtianyan/plugins/webui-aria2/css/modals.css
mtianyan/plugins/webui-aria2/css/style.css
mtianyan/plugins/webui-aria2/flags/1x1/ad.svg
mtianyan/plugins/webui-aria2/flags/1x1/ae.svg
mtianyan/plugins/webui-aria2/flags/1x1/af.svg
mtianyan/plugins/webui-aria2/flags/1x1/ag.svg
mtianyan/plugins/webui-aria2/flags/1x1/ai.svg
mtianyan/plugins/webui-aria2/flags/1x1/al.svg
mtianyan/plugins/webui-aria2/flags/1x1/am.svg
mtianyan-0.0.8.dist-info/DESCRIPTION.rst
mtianyan-0.0.8.dist-info/METADATA
mtianyan-0.0.8.dist-info/RECORD
mtianyan-0.0.8.dist-info/WHEEL
mtianyan-0.0.8.dist-info/metadata.json
mtianyan-0.0.8.dist-info/top_level.txt
